{"type":"PR","pr":{"number":78,"head":"4e34c786e554a5b26804d89742a140336409c8fd"},"user":"Gregory Reardon","status":"draft","branch":"cms/transactions-on-haptics-early-submission","collection":"presenting","title":"IEEE Transactions on Haptics Short Papers","description":"Building on its successful introduction in 2020, the 2022 Haptics Symposium will again feature a IEEE Transactions on Haptics journal track.  Papers accepted to this track will be presented at the conference and simultaneously published as short papers in IEEE Transactions on Haptics. These papers are up to 6 pages in length, including references.","objects":{"entry":{"path":"site/content/presenting/transactions-on-haptics-early-submission.md","sha":"6730af76ab5974d2a27162af72c04e51a04fe329"},"files":[]},"timeStamp":"2021-12-22T02:32:48.939Z"}